{
    "key": "group_60c521d21e5ed",
    "title": "Basic Content Block",
    "fields": [
        {
            "key": "field_60c521ea9667c",
            "label": "Content",
            "name": "",
            "type": "tab",
            "instructions": "",
            "required": 0,
            "conditional_logic": 0,
            "wrapper": {
                "width": "",
                "class": "",
                "id": ""
            },
            "placement": "top",
            "endpoint": 0
        },
        {
            "key": "field_60c522ea96683",
            "label": "Heading",
            "name": "heading",
            "type": "group",
            "instructions": "",
            "required": 0,
            "conditional_logic": 0,
            "wrapper": {
                "width": "",
                "class": "",
                "id": ""
            },
            "layout": "block",
            "sub_fields": [
                {
                    "key": "field_60cbba1cf2dd2",
                    "label": "Text",
                    "name": "text",
                    "type": "text",
                    "instructions": "",
                    "required": 0,
                    "conditional_logic": 0,
                    "wrapper": {
                        "width": "",
                        "class": "",
                        "id": ""
                    },
                    "default_value": "",
                    "placeholder": "",
                    "prepend": "",
                    "append": "",
                    "maxlength": ""
                },
                {
                    "key": "field_60cbba28f2dd3",
                    "label": "Size",
                    "name": "size",
                    "type": "select",
                    "instructions": "",
                    "required": 0,
                    "conditional_logic": 0,
                    "wrapper": {
                        "width": "",
                        "class": "",
                        "id": ""
                    },
                    "choices": {
                        "h1": "h1",
                        "h2": "h2",
                        "h3": "h3",
                        "h4": "h4",
                        "h5": "h5",
                        "h6": "h6"
                    },
                    "default_value": false,
                    "allow_null": 0,
                    "multiple": 0,
                    "ui": 0,
                    "return_format": "value",
                    "ajax": 0,
                    "placeholder": ""
                },
                {
                    "key": "field_60cbba2cf2dd4",
                    "label": "Color",
                    "name": "color",
                    "type": "color_picker",
                    "instructions": "",
                    "required": 0,
                    "conditional_logic": 0,
                    "wrapper": {
                        "width": "",
                        "class": "",
                        "id": ""
                    },
                    "default_value": "#005c97"
                }
            ]
        },
        {
            "key": "field_6127b439facd0",
            "label": "Sub_Heading",
            "name": "sub_heading",
            "type": "group",
            "instructions": "",
            "required": 0,
            "conditional_logic": 0,
            "wrapper": {
                "width": "",
                "class": "",
                "id": ""
            },
            "layout": "block",
            "sub_fields": [
                {
                    "key": "field_6127b439facd1",
                    "label": "Text",
                    "name": "text",
                    "type": "text",
                    "instructions": "",
                    "required": 0,
                    "conditional_logic": 0,
                    "wrapper": {
                        "width": "",
                        "class": "",
                        "id": ""
                    },
                    "default_value": "",
                    "placeholder": "",
                    "prepend": "",
                    "append": "",
                    "maxlength": ""
                },
                {
                    "key": "field_6127b439facd2",
                    "label": "Size",
                    "name": "size",
                    "type": "select",
                    "instructions": "",
                    "required": 0,
                    "conditional_logic": 0,
                    "wrapper": {
                        "width": "",
                        "class": "",
                        "id": ""
                    },
                    "choices": {
                        "h1": "h1",
                        "h2": "h2",
                        "h3": "h3",
                        "h4": "h4",
                        "h5": "h5",
                        "h6": "h6"
                    },
                    "default_value": false,
                    "allow_null": 0,
                    "multiple": 0,
                    "ui": 0,
                    "ajax": 0,
                    "return_format": "value",
                    "placeholder": ""
                },
                {
                    "key": "field_6127b439facd3",
                    "label": "Color",
                    "name": "color",
                    "type": "color_picker",
                    "instructions": "",
                    "required": 0,
                    "conditional_logic": 0,
                    "wrapper": {
                        "width": "",
                        "class": "",
                        "id": ""
                    },
                    "default_value": "#005c97"
                }
            ]
        },
        {
            "key": "field_60c522ee96684",
            "label": "Description",
            "name": "description",
            "type": "wysiwyg",
            "instructions": "",
            "required": 0,
            "conditional_logic": 0,
            "wrapper": {
                "width": "",
                "class": "",
                "id": ""
            },
            "default_value": "",
            "tabs": "all",
            "toolbar": "full",
            "media_upload": 1,
            "delay": 0
        },
        {
            "key": "field_60c522f796685",
            "label": "Images",
            "name": "images",
            "type": "repeater",
            "instructions": "",
            "required": 0,
            "conditional_logic": 0,
            "wrapper": {
                "width": "",
                "class": "",
                "id": ""
            },
            "collapsed": "",
            "min": 0,
            "max": 0,
            "layout": "table",
            "button_label": "",
            "sub_fields": [
                {
                    "key": "field_60ce3a19c33f5",
                    "label": "Display",
                    "name": "display",
                    "type": "true_false",
                    "instructions": "",
                    "required": 0,
                    "conditional_logic": 0,
                    "wrapper": {
                        "width": "",
                        "class": "",
                        "id": ""
                    },
                    "message": "",
                    "default_value": 0,
                    "ui": 0,
                    "ui_on_text": "",
                    "ui_off_text": ""
                },
                {
                    "key": "field_60c5230096686",
                    "label": "Image",
                    "name": "image",
                    "type": "image",
                    "instructions": "",
                    "required": 0,
                    "conditional_logic": 0,
                    "wrapper": {
                        "width": "",
                        "class": "",
                        "id": ""
                    },
                    "return_format": "array",
                    "preview_size": "medium",
                    "library": "all",
                    "min_width": "",
                    "min_height": "",
                    "min_size": "",
                    "max_width": "",
                    "max_height": "",
                    "max_size": "",
                    "mime_types": ""
                }
            ]
        },
        {
            "key": "field_60c521ff9667d",
            "label": "Background",
            "name": "",
            "type": "tab",
            "instructions": "",
            "required": 0,
            "conditional_logic": 0,
            "wrapper": {
                "width": "",
                "class": "",
                "id": ""
            },
            "placement": "top",
            "endpoint": 0
        },
        {
            "key": "field_60c522119667e",
            "label": "Background Type",
            "name": "background_type",
            "type": "select",
            "instructions": "",
            "required": 0,
            "conditional_logic": 0,
            "wrapper": {
                "width": "",
                "class": "",
                "id": ""
            },
            "choices": {
                "colored": "Colored",
                "image": "Image"
            },
            "default_value": false,
            "allow_null": 0,
            "multiple": 0,
            "ui": 0,
            "return_format": "value",
            "ajax": 0,
            "placeholder": ""
        },
        {
            "key": "field_60c522309667f",
            "label": "Background Color",
            "name": "background_color",
            "type": "color_picker",
            "instructions": "",
            "required": 0,
            "conditional_logic": [
                [
                    {
                        "field": "field_60c522119667e",
                        "operator": "==",
                        "value": "colored"
                    }
                ]
            ],
            "wrapper": {
                "width": "",
                "class": "",
                "id": ""
            },
            "default_value": "#FFFFFF"
        },
        {
            "key": "field_60c5224896680",
            "label": "Background Image",
            "name": "background_image",
            "type": "image",
            "instructions": "",
            "required": 0,
            "conditional_logic": [
                [
                    {
                        "field": "field_60c522119667e",
                        "operator": "==",
                        "value": "image"
                    }
                ]
            ],
            "wrapper": {
                "width": "",
                "class": "",
                "id": ""
            },
            "return_format": "array",
            "preview_size": "medium",
            "library": "all",
            "min_width": "",
            "min_height": "",
            "min_size": "",
            "max_width": "",
            "max_height": "",
            "max_size": "",
            "mime_types": ""
        },
        {
            "key": "field_60c5228896681",
            "label": "Miscellaneous",
            "name": "",
            "type": "tab",
            "instructions": "",
            "required": 0,
            "conditional_logic": 0,
            "wrapper": {
                "width": "",
                "class": "",
                "id": ""
            },
            "placement": "top",
            "endpoint": 0
        },
        {
            "key": "field_60c5229696682",
            "label": "Text alignment",
            "name": "text_alignment",
            "type": "select",
            "instructions": "",
            "required": 0,
            "conditional_logic": 0,
            "wrapper": {
                "width": "",
                "class": "",
                "id": ""
            },
            "choices": {
                "center": "Center",
                "left": "Left",
                "right": "Right"
            },
            "default_value": false,
            "allow_null": 0,
            "multiple": 0,
            "ui": 0,
            "return_format": "value",
            "ajax": 0,
            "placeholder": ""
        },
        {
            "key": "field_60ccf3840245a",
            "label": "Text Color",
            "name": "text_color",
            "type": "color_picker",
            "instructions": "",
            "required": 0,
            "conditional_logic": 0,
            "wrapper": {
                "width": "",
                "class": "",
                "id": ""
            },
            "default_value": "#000000"
        },
        {
            "key": "field_60c523e74932d",
            "label": "Padding",
            "name": "padding",
            "type": "select",
            "instructions": "",
            "required": 0,
            "conditional_logic": 0,
            "wrapper": {
                "width": "",
                "class": "",
                "id": ""
            },
            "choices": {
                "small": "Small",
                "medium": "Medium",
                "big": "Big"
            },
            "default_value": false,
            "allow_null": 0,
            "multiple": 0,
            "ui": 0,
            "return_format": "value",
            "ajax": 0,
            "placeholder": ""
        }
    ],
    "location": [
        [
            {
                "param": "block",
                "operator": "==",
                "value": "acf\/basic-content"
            }
        ]
    ],
    "menu_order": 0,
    "position": "normal",
    "style": "default",
    "label_placement": "top",
    "instruction_placement": "label",
    "hide_on_screen": "",
    "active": true,
    "description": "",
    "modified": 1629992350
}